llama_index/indices/managed/vectara/__init__.py
llama_index/indices/managed/vectara/base.py
llama_index/indices/managed/vectara/prompts.py
llama_index/indices/managed/vectara/query.py
llama_index/indices/managed/vectara/retriever.py
llama_index_indices_managed_vectara-0.5.1.dist-info/METADATA
llama_index_indices_managed_vectara-0.5.1.dist-info/WHEEL
llama_index_indices_managed_vectara-0.5.1.dist-info/licenses/LICENSE
llama_index_indices_managed_vectara-0.5.1.dist-info/RECORD
