Metadata-Version: 2.4
Name: llama-index-indices-managed-vectara
Version: 0.5.1
Summary: llama-index managed vectara integration
Author-email: David Oplatka <david.oplatka@vectara.com>, Ofer Mendelevitch <ofer@vectara.com>
License-Expression: MIT
License-File: LICENSE
Requires-Python: <4.0,>=3.9
Requires-Dist: llama-index-core<0.15,>=0.13.0
